pump_fun_api/__init__.py
pump_fun_api-1.0.7.dist-info/METADATA
pump_fun_api-1.0.7.dist-info/WHEEL
pump_fun_api-1.0.7.dist-info/RECORD
