Metadata-Version: 2.1
Name: pump_fun_api
Version: 1.0.7
Summary: Python library to interact with pump.fun frontend API.
Author: Gaibod
Requires-Python: >=3.10,<4.0
Classifier: Programming Language :: Python :: 3
Classifier: Programming Language :: Python :: 3.10
Classifier: Programming Language :: Python :: 3.11
Classifier: Programming Language :: Python :: 3.12
Requires-Dist: requests (>=2.32.2,<3.0.0)
